bandera/__init__.py
bandera-1.0.0.dist-info/METADATA
bandera-1.0.0.dist-info/WHEEL
bandera-1.0.0.dist-info/top_level.txt
bandera-1.0.0.dist-info/RECORD
